{
    "Fungal infection": "Mantar Enfeksiyonu",
    "Allergy": "Alerji",
    "GERD": "GERD (Gastroözofageal Reflü Hastalığı)",
    "Chronic cholestasis": "Kronik Kolestaz",
    "Drug Reaction": "İlaç Reaksiyonu",
    "Peptic ulcer diseae": "Peptik Ülser Hastalığı",
    "AIDS": "AIDS",
    "Diabetes": "Diyabet",
    "Gastroenteritis": "Gastroenterit",
    "Bronchial Asthma": "Bronşiyal Astım",
    "Hypertension": "Hipertansiyon",
    "Migraine": "Migren",
    "Cervical spondylosis": "Servikal Spondiloz",
    "Paralysis (brain hemorrhage)": "Felç (beyin kanaması)",
    "Jaundice": "Sarılık",
    "Malaria": "Sıtma",
    "Chicken pox": "Suçiçeği",
    "Dengue": "Dengue",
    "Typhoid": "Tifo",
    "hepatitis A": "Hepatit A",
    "Hepatitis B": "Hepatit B",
    "Hepatitis C": "Hepatit C",
    "Hepatitis D": "Hepatit D",
    "Hepatitis E": "Hepatit E",
    "Alcoholic hepatitis": "Alkolik Hepatit",
    "Tuberculosis": "Tüberküloz",
    "Common Cold": "Soğuk Algınlığı",
    "Pneumonia": "Zatürre",
    "Dimorphic hemmorhoids(piles)": "Dimorfik Hemoroidler (makat çatlakları)",
    "Heart attack": "Kalp Krizi",
    "Varicose veins": "Varis",
    "Hypothyroidism": "Hipotiroidizm",
    "Hyperthyroidism": "Hipertiroidizm",
    "Hypoglycemia": "Hipoglisemi",
    "Osteoarthristis": "Osteoartrit",
    "Arthritis": "Artrit",
    "(vertigo) Paroymsal  Positional Vertigo": "(Vertigo) Paroksismal Pozisyonel Vertigo",
    "Acne": "Sivilce",
    "Urinary tract infection": "Üriner Sistem Enfeksiyonu",
    "Psoriasis": "Psoriasis (Sedef Hastalığı)",
    "Impetigo": "Impetigo"
}